MANIFEST.in
requirements.txt
setup.py
lisa/__init__.py
lisa/plugins/__init__.py
lisa/plugins/Wifiledlamps/README.rst
lisa/plugins/Wifiledlamps/__init__.py
lisa/plugins/Wifiledlamps/wifiledlamps.json
lisa/plugins/Wifiledlamps/lang/en/LC_MESSAGES/wifiledlamps.po
lisa/plugins/Wifiledlamps/lang/fr/LC_MESSAGES/wifiledlamps.po
lisa/plugins/Wifiledlamps/modules/__init__.py
lisa/plugins/Wifiledlamps/modules/wifiledlamps.py
lisa/plugins/Wifiledlamps/tests/wifileds_test.py
lisa/plugins/Wifiledlamps/web/__init__.py
lisa/plugins/Wifiledlamps/web/api.py
lisa/plugins/Wifiledlamps/web/models.py
lisa/plugins/Wifiledlamps/web/tests.py
lisa/plugins/Wifiledlamps/web/urls.py
lisa/plugins/Wifiledlamps/web/views.py
lisa_plugin_Wifiledlamps.egg-info/PKG-INFO
lisa_plugin_Wifiledlamps.egg-info/SOURCES.txt
lisa_plugin_Wifiledlamps.egg-info/dependency_links.txt
lisa_plugin_Wifiledlamps.egg-info/namespace_packages.txt
lisa_plugin_Wifiledlamps.egg-info/requires.txt
lisa_plugin_Wifiledlamps.egg-info/top_level.txt